pyexcel_xls/__init__.py
pyexcel_xls/xlsr.py
pyexcel_xls/xlsw.py
pyexcel_xls-0.6.1.dist-info/LICENSE
pyexcel_xls-0.6.1.dist-info/METADATA
pyexcel_xls-0.6.1.dist-info/WHEEL
pyexcel_xls-0.6.1.dist-info/top_level.txt
pyexcel_xls-0.6.1.dist-info/RECORD
