Metadata-Version: 1.2
Name: pyexcel-xls
Version: 0.6.1
Summary: A wrapper library to read, manipulate and write data in xls format. Itreads xlsx and xlsm format
Home-page: https://github.com/pyexcel/pyexcel-xls
Author: C.W.
Author-email: info@pyexcel.org
License: New BSD
Download-URL: https://github.com/pyexcel/pyexcel-xls/archive/0.6.1.tar.gz
Keywords: python,xls,xlsx,xlsm
Platform: UNKNOWN
Classifier: Topic :: Software Development :: Libraries
Classifier: Programming Language :: Python
Classifier: Intended Audience :: Developers
Classifier: Programming Language :: Python :: 3 :: Only
Classifier: Programming Language :: Python :: 3.6
Classifier: Programming Language :: Python :: 3.7
Classifier: Programming Language :: Python :: 3.8
Classifier: Programming Language :: Python :: Implementation :: PyPy
Requires-Python: >=3.6
